nectarclient_lib/__init__.py
nectarclient_lib/base.py
nectarclient_lib/exceptions.py
nectarclient_lib/osc/__init__.py
nectarclient_lib/osc/utils.py
nectarclient_lib/tests/__init__.py
nectarclient_lib/tests/unit/__init__.py
nectarclient_lib/tests/unit/fakes.py
nectarclient_lib/tests/unit/test_base.py
nectarclient_lib/tests/unit/test_exceptions.py
nectarclient_lib/tests/unit/utils.py
nectarclient_lib-1.4.0.dist-info/LICENSE
nectarclient_lib-1.4.0.dist-info/METADATA
nectarclient_lib-1.4.0.dist-info/WHEEL
nectarclient_lib-1.4.0.dist-info/pbr.json
nectarclient_lib-1.4.0.dist-info/top_level.txt
nectarclient_lib-1.4.0.dist-info/RECORD
